design/hex_display.v
module hex_display (
    input wire [2:0] state_in,
    output reg [6:0] hex2, // Leftmost of the 3
    output reg [6:0] hex1, // Middle
    output reg [6:0] hex0  // Rightmost
);

    // Active low 7-segment encoding
    localparam CHAR_O = 7'h40;
    localparam CHAR_P = 7'h0C;
    localparam CHAR_n = 7'h2B;
    
    localparam CHAR_E = 7'h06;
    localparam CHAR_r = 7'h2F;
    
    localparam CHAR_C = 7'h46;
    localparam CHAR_h = 7'h0B;
    localparam CHAR_g = 7'h10;
    
    localparam CHAR_DASH = 7'h3F;

    always @(*) begin
        case (state_in)
            3'd0: begin // IDLE
                hex2 = CHAR_DASH;
                hex1 = CHAR_DASH;
                hex0 = CHAR_DASH;
            end
            3'd1: begin // OPN
                hex2 = CHAR_O;
                hex1 = CHAR_P;
                hex0 = CHAR_n;
            end
            3'd2: begin // ERR
                hex2 = CHAR_E;
                hex1 = CHAR_r;
                hex0 = CHAR_r;
            end
            3'd3: begin // CHG
                hex2 = CHAR_C;
                hex1 = CHAR_h;
                hex0 = CHAR_g;
            end
            default: begin
                hex2 = CHAR_DASH;
                hex1 = CHAR_DASH;
                hex0 = CHAR_DASH;
            end
        endcase
    end

endmodule

design/lock_fsm.v
module lock_fsm (
    input wire clk,
    input wire rst_n,
    
    // User interface
    input wire [7:0] sw_in,
    input wire enter_btn_tick,
    input wire change_btn_tick,
    
    // SRAM controller interface
    output reg sram_rd_en,
    output reg sram_wr_en,
    output reg [18:0] sram_addr,
    output reg [15:0] sram_data_in,
    input wire [15:0] sram_data_out,
    input wire sram_ready,
    
    // Outputs
    output reg led_red,
    output reg led_green,
    output reg [2:0] display_state // 0: Blank/Line, 1: OPN, 2: ERR, 3: CHG
);

    localparam S_INIT_WR    = 4'd0;
    localparam S_INIT_WAIT  = 4'd1;
    localparam S_IDLE       = 4'd2;
    localparam S_READ_CHECK = 4'd3;
    localparam S_WAIT_CHECK = 4'd4;
    localparam S_UNLOCKED   = 4'd5;
    localparam S_ERR        = 4'd6;
    localparam S_WRITE_CHG  = 4'd7;
    localparam S_WAIT_CHG   = 4'd8;
    localparam S_CHG_DONE   = 4'd9;

    reg [3:0] state;
    reg [27:0] timer; // 50MHz, 2 seconds = 100,000,000 cycles
    localparam TIMER_2SEC = 28'd100_000_000;

    always @(posedge clk or negedge rst_n) begin
        if (!rst_n) begin
            state <= S_INIT_WR;
            sram_rd_en <= 1'b0;
            sram_wr_en <= 1'b0;
            sram_addr <= 19'd0;
            sram_data_in <= 16'd0;
            led_red <= 1'b1; // Locked by default
            led_green <= 1'b0;
            display_state <= 3'd0;
            timer <= 28'd0;
        end else begin
            case (state)
                S_INIT_WR: begin
                    sram_wr_en <= 1'b1;
                    sram_addr <= 19'd0;
                    sram_data_in <= 16'h0000; // Default password is 00
                    state <= S_INIT_WAIT;
                end
                
                S_INIT_WAIT: begin
                    if (sram_ready) begin
                        sram_wr_en <= 1'b0;
                        state <= S_IDLE;
                    end
                end
                
                S_IDLE: begin
                    led_red <= 1'b1;
                    led_green <= 1'b0;
                    display_state <= 3'd0; // Idle display
                    
                    if (enter_btn_tick) begin
                        sram_rd_en <= 1'b1;
                        sram_addr <= 19'd0;
                        state <= S_READ_CHECK;
                    end
                end
                
                S_READ_CHECK: begin
                    if (sram_ready) begin
                        // Data is available
                        if (sram_data_out[7:0] == sw_in) begin
                            state <= S_UNLOCKED;
                        end else begin
                            state <= S_ERR;
                            timer <= 28'd0;
                        end
                        sram_rd_en <= 1'b0;
                    end
                end
                
                S_UNLOCKED: begin
                    led_red <= 1'b0;
                    led_green <= 1'b1;
                    display_state <= 3'd1; // OPN
                    
                    if (change_btn_tick) begin
                        // Change password
                        sram_wr_en <= 1'b1;
                        sram_addr <= 19'd0;
                        sram_data_in <= {8'h00, sw_in}; // Write new password from SW
                        state <= S_WRITE_CHG;
                    end else if (enter_btn_tick) begin
                        // Lock again
                        state <= S_IDLE;
                    end
                end
                
                S_ERR: begin
                    led_red <= 1'b1;
                    led_green <= 1'b0;
                    display_state <= 3'd2; // ERR
                    
                    if (timer < TIMER_2SEC) begin
                        timer <= timer + 1'b1;
                    end else begin
                        state <= S_IDLE;
                    end
                    
                    // Allow early exit from ERR state if enter is pressed again
                    if (enter_btn_tick) begin
                        state <= S_IDLE;
                    end
                end
                
                S_WRITE_CHG: begin
                    if (sram_ready) begin
                        sram_wr_en <= 1'b0;
                        state <= S_CHG_DONE;
                        timer <= 28'd0;
                    end
                end
                
                S_CHG_DONE: begin
                    led_red <= 1'b0;
                    led_green <= 1'b1; // Still unlocked
                    display_state <= 3'd3; // CHG
                    
                    if (timer < TIMER_2SEC) begin
                        timer <= timer + 1'b1;
                    end else begin
                        state <= S_UNLOCKED; // Go back to unlocked state after showing CHG
                    end
                end
                
                default: state <= S_INIT_WR;
            endcase
        end
    end

endmodule

design/sram_controller.v
module sram_controller (
    input wire clk,
    input wire rst_n,
    
    // User interface
    input wire rd_en,
    input wire wr_en,
    input wire [18:0] addr_in,
    input wire [15:0] data_in,
    output reg [15:0] data_out,
    output reg ready,
    
    // SRAM physical interface
    inout wire [15:0] SRAM_DQ,
    output reg [18:0] SRAM_ADDR,
    output reg SRAM_CE_N,
    output reg SRAM_WE_N,
    output reg SRAM_OE_N,
    output wire SRAM_UB_N,
    output wire SRAM_LB_N
);

    // Byte enables always active (we use 16-bit words)
    assign SRAM_UB_N = 1'b0;
    assign SRAM_LB_N = 1'b0;

    localparam IDLE    = 3'd0;
    localparam R_WAIT  = 3'd1;
    localparam R_DONE  = 3'd2;
    localparam W_SETUP = 3'd3;
    localparam W_WAIT  = 3'd4;
    localparam W_DONE  = 3'd5;

    reg [2:0] state;
    
    // Control bus tri-state
    reg drive_data;
    reg [15:0] data_to_write;
    
    assign SRAM_DQ = drive_data ? data_to_write : 16'hzzzz;

    always @(posedge clk or negedge rst_n) begin
        if (!rst_n) begin
            state <= IDLE;
            ready <= 1'b0;
            data_out <= 16'd0;
            SRAM_ADDR <= 19'd0;
            SRAM_CE_N <= 1'b1;
            SRAM_WE_N <= 1'b1;
            SRAM_OE_N <= 1'b1;
            drive_data <= 1'b0;
            data_to_write <= 16'd0;
        end else begin
            case (state)
                IDLE: begin
                    ready <= 1'b0;
                    SRAM_CE_N <= 1'b1;
                    SRAM_WE_N <= 1'b1;
                    SRAM_OE_N <= 1'b1;
                    drive_data <= 1'b0;
                    
                    if (wr_en) begin
                        SRAM_ADDR <= addr_in;
                        data_to_write <= data_in;
                        state <= W_SETUP;
                    end else if (rd_en) begin
                        SRAM_ADDR <= addr_in;
                        state <= R_WAIT;
                        SRAM_CE_N <= 1'b0;
                        SRAM_OE_N <= 1'b0;
                    end
                end
                
                R_WAIT: begin
                    // One cycle wait for data to be valid from SRAM
                    // SRAM guarantees 10ns, clk is 20ns, so it's ready now
                    data_out <= SRAM_DQ;
                    ready <= 1'b1;
                    state <= R_DONE;
                end
                
                R_DONE: begin
                    // Wait for rd_en to go low before returning to IDLE
                    if (!rd_en) begin
                        state <= IDLE;
                        SRAM_CE_N <= 1'b1;
                        SRAM_OE_N <= 1'b1;
                        ready <= 1'b0;
                    end
                end
                
                W_SETUP: begin
                    // Address is stable, now assert CE, WE, and drive Data
                    SRAM_CE_N <= 1'b0;
                    SRAM_WE_N <= 1'b0;
                    drive_data <= 1'b1;
                    state <= W_WAIT;
                end
                
                W_WAIT: begin
                    // Hold WE low for 1 cycle, then deassert
                    SRAM_WE_N <= 1'b1;
                    ready <= 1'b1;
                    state <= W_DONE;
                end
                
                W_DONE: begin
                    // Wait for wr_en to go low
                    if (!wr_en) begin
                        state <= IDLE;
                        SRAM_CE_N <= 1'b1;
                        drive_data <= 1'b0;
                        ready <= 1'b0;
                    end
                end
                
                default: state <= IDLE;
            endcase
        end
    end

endmodule

design/button_debounce.v
module button_debounce (
    input wire clk,
    input wire rst_n,
    input wire btn_in,
    output reg btn_out
);

    // 20ms debounce at 50MHz is 1,000,000 clock cycles.
    // 20 bits can hold up to 1,048,575
    reg [19:0] counter;
    reg btn_sync_0;
    reg btn_sync_1;

    // Double flip-flop synchronizer
    always @(posedge clk or negedge rst_n) begin
        if (!rst_n) begin
            btn_sync_0 <= 1'b1; // Assuming active low buttons (common on DE boards)
            btn_sync_1 <= 1'b1;
        end else begin
            btn_sync_0 <= btn_in;
            btn_sync_1 <= btn_sync_0;
        end
    end

    always @(posedge clk or negedge rst_n) begin
        if (!rst_n) begin
            counter <= 20'd0;
            btn_out <= 1'b1; // Default unpressed
        end else begin
            if (btn_sync_1 == btn_out) begin
                counter <= 20'd0; // Reset counter if no change
            end else begin
                counter <= counter + 1'b1;
                if (counter == 20'd1_000_000) begin
                    btn_out <= btn_sync_1; // Update output after stable 20ms
                    counter <= 20'd0;
                end
            end
        end
    end

endmodule

design/digital_safe_lock.v
module digital_safe_lock (
    input wire CLOCK_50,
    input wire [7:0] SW,
    input wire [2:0] KEY, // KEY[0]: rst_n, KEY[1]: Enter, KEY[2]: Change Pass
    
    output wire [0:0] LEDR, // Red LED for locked/error
    output wire [0:0] LEDG, // Green LED for unlocked
    
    output wire [6:0] HEX2,
    output wire [6:0] HEX1,
    output wire [6:0] HEX0,
    
    // SRAM interface
    inout wire [15:0] SRAM_DQ,
    output wire [18:0] SRAM_ADDR,
    output wire SRAM_CE_N,
    output wire SRAM_WE_N,
    output wire SRAM_OE_N,
    output wire SRAM_UB_N,
    output wire SRAM_LB_N
);

    wire rst_n = KEY[0];
    
    // Debounce buttons
    wire enter_btn_db;
    wire change_btn_db;
    
    button_debounce db_enter (
        .clk(CLOCK_50),
        .rst_n(rst_n),
        .btn_in(KEY[1]),
        .btn_out(enter_btn_db)
    );
    
    button_debounce db_change (
        .clk(CLOCK_50),
        .rst_n(rst_n),
        .btn_in(KEY[2]),
        .btn_out(change_btn_db)
    );
    
    // Edge detection for debounced buttons (active low -> detect falling edge)
    reg enter_btn_db_reg;
    reg change_btn_db_reg;
    
    always @(posedge CLOCK_50 or negedge rst_n) begin
        if (!rst_n) begin
            enter_btn_db_reg <= 1'b1;
            change_btn_db_reg <= 1'b1;
        end else begin
            enter_btn_db_reg <= enter_btn_db;
            change_btn_db_reg <= change_btn_db;
        end
    end
    
    wire enter_tick = (enter_btn_db_reg == 1'b1) && (enter_btn_db == 1'b0);
    wire change_tick = (change_btn_db_reg == 1'b1) && (change_btn_db == 1'b0);
    
    // SRAM Controller connections
    wire sram_rd_en;
    wire sram_wr_en;
    wire [18:0] sram_addr;
    wire [15:0] sram_data_in;
    wire [15:0] sram_data_out;
    wire sram_ready;
    
    sram_controller sram_ctrl (
        .clk(CLOCK_50),
        .rst_n(rst_n),
        .rd_en(sram_rd_en),
        .wr_en(sram_wr_en),
        .addr_in(sram_addr),
        .data_in(sram_data_in),
        .data_out(sram_data_out),
        .ready(sram_ready),
        .SRAM_DQ(SRAM_DQ),
        .SRAM_ADDR(SRAM_ADDR),
        .SRAM_CE_N(SRAM_CE_N),
        .SRAM_WE_N(SRAM_WE_N),
        .SRAM_OE_N(SRAM_OE_N),
        .SRAM_UB_N(SRAM_UB_N),
        .SRAM_LB_N(SRAM_LB_N)
    );
    
    // Lock FSM connections
    wire [2:0] display_state;
    
    lock_fsm fsm_inst (
        .clk(CLOCK_50),
        .rst_n(rst_n),
        .sw_in(SW),
        .enter_btn_tick(enter_tick),
        .change_btn_tick(change_tick),
        .sram_rd_en(sram_rd_en),
        .sram_wr_en(sram_wr_en),
        .sram_addr(sram_addr),
        .sram_data_in(sram_data_in),
        .sram_data_out(sram_data_out),
        .sram_ready(sram_ready),
        .led_red(LEDR[0]),
        .led_green(LEDG[0]),
        .display_state(display_state)
    );
    
    // HEX Display connections
    hex_display hex_inst (
        .state_in(display_state),
        .hex2(HEX2),
        .hex1(HEX1),
        .hex0(HEX0)
    );

endmodule

tb/tb_digital_safe_lock.v
`timescale 1ns/1ps

module tb_digital_safe_lock();

    reg CLOCK_50;
    reg [7:0] SW;
    reg [2:0] KEY;
    
    wire LEDR;
    wire LEDG;
    wire [6:0] HEX2;
    wire [6:0] HEX1;
    wire [6:0] HEX0;
    
    wire [15:0] SRAM_DQ;
    wire [18:0] SRAM_ADDR;
    wire SRAM_CE_N;
    wire SRAM_WE_N;
    wire SRAM_OE_N;
    wire SRAM_UB_N;
    wire SRAM_LB_N;

    // Instantiate Top Module
    digital_safe_lock dut (
        .CLOCK_50(CLOCK_50),
        .SW(SW),
        .KEY(KEY),
        .LEDR(LEDR),
        .LEDG(LEDG),
        .HEX2(HEX2),
        .HEX1(HEX1),
        .HEX0(HEX0),
        .SRAM_DQ(SRAM_DQ),
        .SRAM_ADDR(SRAM_ADDR),
        .SRAM_CE_N(SRAM_CE_N),
        .SRAM_WE_N(SRAM_WE_N),
        .SRAM_OE_N(SRAM_OE_N),
        .SRAM_UB_N(SRAM_UB_N),
        .SRAM_LB_N(SRAM_LB_N)
    );

    // Simple SRAM Model
    reg [15:0] sram_mem [0:1023]; // Only model first 1024 words
    reg [15:0] sram_data_out;
    reg sram_drive_data;
    
    assign SRAM_DQ = sram_drive_data ? sram_data_out : 16'hzzzz;
    
    always @(*) begin
        sram_drive_data = 1'b0;
        sram_data_out = 16'hxxxx;
        
        if (!SRAM_CE_N) begin
            if (!SRAM_WE_N) begin
                // Write cycle
                // Note: Real SRAM writes when WE or CE goes high, but simplified behavioral here
                sram_mem[SRAM_ADDR] <= SRAM_DQ;
            end else if (!SRAM_OE_N) begin
                // Read cycle
                sram_drive_data = 1'b1;
                sram_data_out = sram_mem[SRAM_ADDR];
            end
        end
    end

    // Clock generation (50MHz = 20ns period)
    initial begin
        CLOCK_50 = 0;
        forever #10 CLOCK_50 = ~CLOCK_50;
    end

    // --- Tasks for Modular Testing ---
    
    // Task 1: Reset the system
    task reset_system;
        begin
            KEY[0] = 1'b0;
            #100 KEY[0] = 1'b1;
            // Wait for INIT state to finish (writing 00 to SRAM)
            #200;
        end
    endtask

    // Task 2: Simulate entering a password via switches and pressing a button
    // btn_type: 1 for Enter (KEY[1]), 2 for Change (KEY[2])
    task enter_password(input [7:0] pass, input [1:0] btn_type);
        begin
            SW = pass;
            if (btn_type == 1) begin
                KEY[1] = 1'b0;
                force dut.enter_btn_db = 1'b0; // Bypass debounce
                #100;
                force dut.enter_btn_db = 1'b1;
                KEY[1] = 1'b1;
            end else if (btn_type == 2) begin
                KEY[2] = 1'b0;
                force dut.change_btn_db = 1'b0; // Bypass debounce
                #100;
                force dut.change_btn_db = 1'b1;
                KEY[2] = 1'b1;
            end
            #200; // wait for FSM to process
        end
    endtask

    // Task 3: Bypass the 2-second timer for "CHG" display
    task bypass_display_timer;
        begin
            force dut.fsm_inst.timer = 28'd100_000_000;
            #100;
            release dut.fsm_inst.timer;
            #200;
        end
    endtask

    // Task 4: Force state back to IDLE (alternative to timer bypass for ERR state)
    task force_to_idle;
        begin
            force dut.fsm_inst.state = 4'd2; // S_IDLE
            #100;
            release dut.fsm_inst.state;
            #100;
        end
    endtask

    // Task 5: Self-checking result verifier
    task check_result(input exp_ledg, input exp_ledr, input [7:0] test_id);
        begin
            if (LEDG == exp_ledg && LEDR == exp_ledr) begin
                $display("Pass: Test %0d (LEDG=%b, LEDR=%b)", test_id, LEDG, LEDR);
            end else begin
                $display("Fail: Test %0d - Expected LEDG=%b LEDR=%b, Got LEDG=%b LEDR=%b", 
                         test_id, exp_ledg, exp_ledr, LEDG, LEDR);
                $stop; // Halt simulation if a test fails
            end
        end
    endtask

    // --- Main Test Sequence ---
    initial begin
        // Optional: Generate waveform
        $dumpfile("waveform.vcd");
        $dumpvars(0, tb_digital_safe_lock);

        // Initialize inputs
        SW = 8'h00;
        KEY = 3'b111; // KEY is active low
        
        $display("========================================");
        $display("   DIGITAL SAFE LOCK - TESTBENCH START  ");
        $display("========================================");
        
        // 1. Reset
        reset_system();
        
        // Test 1: Unlock with default password 00
        $display("\n[Test 1] Unlock with default password (00)");
        enter_password(8'h00, 1);
        check_result(1'b1, 1'b0, 1);
        
        // Test 2: Change password to A5
        $display("\n[Test 2] Change password to A5");
        enter_password(8'hA5, 2);
        bypass_display_timer();
        $display("Password changed to A5.");
        
        // Lock it back
        $display("\nLocking the safe...");
        enter_password(8'hA5, 1);
        
        // Test 3: Try unlocking with WRONG password 11
        $display("\n[Test 3] Try unlocking with WRONG password (11)");
        enter_password(8'h11, 1);
        check_result(1'b0, 1'b1, 3); // Expect Red LED for wrong pass
        force_to_idle(); // Bypass the 2-second error display
        
        // Test 4: Unlock with NEW password A5
        $display("\n[Test 4] Unlock with NEW password (A5)");
        enter_password(8'hA5, 1);
        check_result(1'b1, 1'b0, 4);
        
        // Lock it back
        $display("\nLocking the safe...");
        enter_password(8'h00, 1); // Password value doesn't matter when locking
        
        // Test 5: Spam Wrong Password
        $display("\n[Test 5] Spam wrong password multiple times");
        enter_password(8'h99, 1);
        check_result(1'b0, 1'b1, 51);
        force_to_idle();
        
        enter_password(8'h88, 1);
        check_result(1'b0, 1'b1, 52);
        force_to_idle();

        // Test 6: Finally unlock it again
        $display("\n[Test 6] Unlock again with correct password (A5)");
        enter_password(8'hA5, 1);
        check_result(1'b1, 1'b0, 6);

        #500;
        $display("========================================");
        $display("          SIMULATION COMPLETE           ");
        $display("========================================");
        $finish;
    end

endmodule

waveform.vcd
$date
	Mon Jun 22 19:18:43 2026
$end
$version
	Icarus Verilog
$end
$timescale
	1ps
$end
$scope module tb_digital_safe_lock $end
$var wire 16 ! SRAM_DQ [15:0] $end
$var wire 1 " SRAM_LB_N $end
$var wire 1 # SRAM_UB_N $end
$var wire 1 $ SRAM_WE_N $end
$var wire 1 % SRAM_OE_N $end
$var wire 1 & SRAM_CE_N $end
$var wire 19 ' SRAM_ADDR [18:0] $end
$var wire 1 ( LEDR $end
$var wire 1 ) LEDG $end
$var wire 7 * HEX2 [6:0] $end
$var wire 7 + HEX1 [6:0] $end
$var wire 7 , HEX0 [6:0] $end
$var reg 1 - CLOCK_50 $end
$var reg 3 . KEY [2:0] $end
$var reg 8 / SW [7:0] $end
$var reg 16 0 sram_data_out [15:0] $end
$var reg 1 1 sram_drive_data $end
$scope module dut $end
$var wire 1 - CLOCK_50 $end
$var wire 3 2 KEY [2:0] $end
$var wire 16 3 SRAM_DQ [15:0] $end
$var wire 1 " SRAM_LB_N $end
$var wire 1 # SRAM_UB_N $end
$var wire 8 4 SW [7:0] $end
$var wire 1 5 change_tick $end
$var wire 1 6 enter_tick $end
$var wire 1 7 sram_wr_en $end
$var wire 1 8 sram_ready $end
$var wire 1 9 sram_rd_en $end
$var wire 16 : sram_data_out [15:0] $end
$var wire 16 ; sram_data_in [15:0] $end
$var wire 19 < sram_addr [18:0] $end
$var wire 1 = rst_n $end
$var wire 1 > enter_btn_db $end
$var wire 3 ? display_state [2:0] $end
$var wire 1 @ change_btn_db $end
$var wire 1 $ SRAM_WE_N $end
$var wire 1 % SRAM_OE_N $end
$var wire 1 & SRAM_CE_N $end
$var wire 19 A SRAM_ADDR [18:0] $end
$var wire 1 ( LEDR $end
$var wire 1 ) LEDG $end
$var wire 7 B HEX2 [6:0] $end
$var wire 7 C HEX1 [6:0] $end
$var wire 7 D HEX0 [6:0] $end
$var reg 1 E change_btn_db_reg $end
$var reg 1 F enter_btn_db_reg $end
$scope module db_change $end
$var wire 1 G btn_in $end
$var wire 1 - clk $end
$var wire 1 = rst_n $end
$var reg 1 @ btn_out $end
$var reg 1 H btn_sync_0 $end
$var reg 1 I btn_sync_1 $end
$var reg 20 J counter [19:0] $end
$upscope $end
$scope module db_enter $end
$var wire 1 K btn_in $end
$var wire 1 - clk $end
$var wire 1 = rst_n $end
$var reg 1 > btn_out $end
$var reg 1 L btn_sync_0 $end
$var reg 1 M btn_sync_1 $end
$var reg 20 N counter [19:0] $end
$upscope $end
$scope module fsm_inst $end
$var wire 1 5 change_btn_tick $end
$var wire 1 - clk $end
$var wire 1 6 enter_btn_tick $end
$var wire 1 = rst_n $end
$var wire 8 O sw_in [7:0] $end
$var wire 1 8 sram_ready $end
$var wire 16 P sram_data_out [15:0] $end
$var parameter 4 Q S_CHG_DONE $end
$var parameter 4 R S_ERR $end
$var parameter 4 S S_IDLE $end
$var parameter 4 T S_INIT_WAIT $end
$var parameter 4 U S_INIT_WR $end
$var parameter 4 V S_READ_CHECK $end
$var parameter 4 W S_UNLOCKED $end
$var parameter 4 X S_WAIT_CHECK $end
$var parameter 4 Y S_WAIT_CHG $end
$var parameter 4 Z S_WRITE_CHG $end
$var parameter 28 [ TIMER_2SEC $end
$var reg 3 \ display_state [2:0] $end
$var reg 1 ) led_green $end
$var reg 1 ( led_red $end
$var reg 19 ] sram_addr [18:0] $end
$var reg 16 ^ sram_data_in [15:0] $end
$var reg 1 9 sram_rd_en $end
$var reg 1 7 sram_wr_en $end
$var reg 4 _ state [3:0] $end
$var reg 28 ` timer [27:0] $end
$upscope $end
$scope module hex_inst $end
$var wire 3 a state_in [2:0] $end
$var parameter 7 b CHAR_C $end
$var parameter 7 c CHAR_DASH $end
$var parameter 7 d CHAR_E $end
$var parameter 7 e CHAR_O $end
$var parameter 7 f CHAR_P $end
$var parameter 7 g CHAR_g $end
$var parameter 7 h CHAR_h $end
$var parameter 7 i CHAR_n $end
$var parameter 7 j CHAR_r $end
$var reg 7 k hex0 [6:0] $end
$var reg 7 l hex1 [6:0] $end
$var reg 7 m hex2 [6:0] $end
$upscope $end
$scope module sram_ctrl $end
$var wire 16 n SRAM_DQ [15:0] $end
$var wire 1 " SRAM_LB_N $end
$var wire 1 # SRAM_UB_N $end
$var wire 19 o addr_in [18:0] $end
$var wire 1 - clk $end
$var wire 16 p data_in [15:0] $end
$var wire 1 9 rd_en $end
$var wire 1 = rst_n $end
$var wire 1 7 wr_en $end
$var parameter 3 q IDLE $end
$var parameter 3 r R_DONE $end
$var parameter 3 s R_WAIT $end
$var parameter 3 t W_DONE $end
$var parameter 3 u W_SETUP $end
$var parameter 3 v W_WAIT $end
$var reg 19 w SRAM_ADDR [18:0] $end
$var reg 1 & SRAM_CE_N $end
$var reg 1 % SRAM_OE_N $end
$var reg 1 $ SRAM_WE_N $end
$var reg 16 x data_out [15:0] $end
$var reg 16 y data_to_write [15:0] $end
$var reg 1 z drive_data $end
$var reg 1 8 ready $end
$var reg 3 { state [2:0] $end
$upscope $end
$upscope $end
$scope task bypass_display_timer $end
$upscope $end
$scope task check_result $end
$var reg 1 | exp_ledg $end
$var reg 1 } exp_ledr $end
$var reg 8 ~ test_id [7:0] $end
$upscope $end
$scope task enter_password $end
$var reg 2 !" btn_type [1:0] $end
$var reg 8 "" pass [7:0] $end
$upscope $end
$scope task force_to_idle $end
$upscope $end
$scope task reset_system $end
$upscope $end
$upscope $end
$enddefinitions $end
$comment Show the parameter values. $end
$dumpall
b100 v
b11 u
b101 t
b1 s
b10 r
b0 q
b101111 j
b101011 i
b1011 h
b10000 g
b1100 f
b1000000 e
b110 d
b111111 c
b1000110 b
b101111101011110000100000000 [
b111 Z
b1000 Y
b100 X
b101 W
b11 V
b0 U
b1 T
b10 S
b110 R
b1001 Q
$end
#0
$dumpvars
bx ""
bx !"
bx ~
x}
x|
b0 {
0z
b0 y
b0 x
b0 w
b0 p
b0 o
bz n
b111111 m
b111111 l
b111111 k
b0 a
b0 `
b0 _
b0 ^
b0 ]
b0 \
b0 P
b0 O
b0 N
1M
1L
1K
b0 J
1I
1H
1G
1F
1E
b111111 D
b111111 C
b111111 B
b0 A
1@
b0 ?
1>
0=
b0 <
b0 ;
b0 :
09
08
07
06
05
b0 4
bz 3
b110 2
01
bx 0
b0 /
b110 .
0-
b111111 ,
b111111 +
b111111 *
0)
1(
b0 '
1&
1%
1$
0#
0"
bz !
$end
#10000
1-
#20000
0-
#30000
1-
#40000
0-
#50000
1-
#60000
0-
#70000
1-
#80000
0-
#90000
1-
#100000
1=
0-
b111 .
b111 2
#110000
b1 _
17
1-
#120000
0-
#130000
b11 {
1-
#140000
0-
#150000
b0 !
b0 3
b0 n
b100 {
1z
0$
0&
1-
#160000
0-
#170000
b101 {
18
1$
1-
#180000
0-
#190000
b10 _
07
1-
#200000
0-
#210000
bz !
bz 3
bz n
08
0z
1&
b0 {
1-
#220000
0-
#230000
1-
#240000
0-
#250000
1-
#260000
0-
#270000
1-
#280000
0-
#290000
1-
#300000
16
0K
0-
0>
b101 .
b101 2
b1 !"
b0 ""
#310000
06
0L
b1 N
b11 _
19
0F
1-
#320000
0-
#330000
b0 !
b0 3
b0 n
b0 0
11
0%
0&
b1 {
b10 N
0M
1-
#340000
0-
#350000
b0 N
b10 {
18
1-
#360000
0-
#370000
09
b101 _
1-
#380000
0-
#390000
bz !
bz 3
bz n
bx 0
01
b101011 ,
b101011 D
b101011 k
b1100 +
b1100 C
b1100 l
b1000000 *
b1000000 B
b1000000 m
08
1%
1&
b0 {
b1 ?
b1 \
b1 a
1)
0(
1-
#400000
1K
0-
b111 .
b111 2
1>
#410000
1F
b1 N
1L
1-
#420000
0-
#430000
1M
b10 N
1-
#440000
0-
#450000
b0 N
1-
#460000
0-
#470000
1-
#480000
0-
#490000
1-
#500000
0-
#510000
1-
#520000
0-
#530000
1-
#540000
0-
#550000
1-
#560000
0-
#570000
1-
#580000
0-
#590000
1-
#600000
15
0G
0-
0@
b11 .
b11 2
b10100101 /
b10100101 4
b10100101 O
b10 !"
b10100101 ""
b1 ~
0}
1|
#610000
05
0E
b111 _
b10100101 ;
b10100101 ^
b10100101 p
17
b1 J
0H
1-
#620000
0-
#630000
0I
b10 J
b11 {
b10100101 y
1-
#640000
0-
#650000
b10100101 !
b10100101 3
b10100101 n
b100 {
1z
0$
0&
b0 J
1-
#660000
0-
#670000
b101 {
18
1$
1-
#680000
0-
#690000
b1001 _
07
1-
#700000
1G
0-
b111 .
b111 2
1@
#710000
bz !
bz 3
bz n
b10000 ,
b10000 D
b10000 k
b1011 +
b1011 C
b1011 l
b1000110 *
b1000110 B
b1000110 m
1H
b1 J
08
0z
1&
b0 {
b1 `
b11 ?
b11 \
b11 a
1E
1-
#720000
0-
#730000
b10 `
b10 J
1I
1-
#740000
0-
#750000
b0 J
b11 `
1-
#760000
0-
#770000
b100 `
1-
#780000
0-
#790000
b101 `
1-
#800000
0-
#810000
b110 `
1-
#820000
0-
#830000
b111 `
1-
#840000
0-
#850000
b1000 `
1-
#860000
0-
#870000
b1001 `
1-
#880000
0-
#890000
b1010 `
1-
#900000
0-
b101111101011110000100000000 `
#910000
b101 _
1-
#920000
0-
#930000
b101011 ,
b101011 D
b101011 k
b1100 +
b1100 C
b1100 l
b1000000 *
b1000000 B
b1000000 m
b1 ?
b1 \
b1 a
1-
#940000
0-
#950000
1-
#960000
0-
#970000
1-
#980000
0-
#990000
1-
#1000000
0-
b101111101011110000100000000 `
#1010000
1-
#1020000
0-
#1030000
1-
#1040000
0-
#1050000
1-
#1060000
0-
#1070000
1-
#1080000
0-
#1090000
1-
#1100000
0-
#1110000
1-
#1120000
0-
#1130000
1-
#1140000
0-
#1150000
1-
#1160000
0-
#1170000
1-
#1180000
0-
#1190000
1-
#1200000
16
0K
0-
0>
b101 .
b101 2
b1 !"
#1210000
06
0F
b10 _
b1 N
0L
1-
#1220000
0-
#1230000
b111111 ,
b111111 D
b111111 k
b111111 +
b111111 C
b111111 l
b111111 *
b111111 B
b111111 m
0M
b10 N
b0 ?
b0 \
b0 a
0)
1(
1-
#1240000
0-
#1250000
b0 N
1-
#1260000
0-
#1270000
1-
#1280000
0-
#1290000
1-
#1300000
1K
0-
b111 .
b111 2
1>
#1310000
1L
b1 N
1F
1-
#1320000
0-
#1330000
b10 N
1M
1-
#1340000
0-
#1350000
b0 N
1-
#1360000
0-
#1370000
1-
#1380000
0-
#1390000
1-
#1400000
0-
#1410000
1-
#1420000
0-
#1430000
1-
#1440000
0-
#1450000
1-
#1460000
0-
#1470000
1-
#1480000
0-
#1490000
1-
#1500000
16
0K
0-
0>
b101 .
b101 2
b10001 /
b10001 4
b10001 O
b10001 ""
#1510000
06
0L
b1 N
b11 _
19
0F
1-
#1520000
0-
#1530000
b10100101 !
b10100101 3
b10100101 n
b10100101 0
11
0%
0&
b1 {
b10 N
0M
1-
#1540000
0-
#1550000
b0 N
b10 {
18
b10100101 :
b10100101 P
b10100101 x
1-
#1560000
0-
#1570000
09
b0 `
b110 _
1-
#1580000
0-
#1590000
bz !
bz 3
bz n
bx 0
01
b101111 ,
b101111 D
b101111 k
b101111 +
b101111 C
b101111 l
b110 *
b110 B
b110 m
08
1%
1&
b0 {
b1 `
b10 ?
b10 \
b10 a
1-
#1600000
1K
0-
b111 .
b111 2
1>
#1610000
1F
b10 `
b1 N
1L
1-
#1620000
0-
#1630000
1M
b10 N
b11 `
1-
#1640000
0-
#1650000
b100 `
b0 N
1-
#1660000
0-
#1670000
b101 `
1-
#1680000
0-
#1690000
b110 `
1-
#1700000
0-
#1710000
b111 `
1-
#1720000
0-
#1730000
b1000 `
1-
#1740000
0-
#1750000
b1001 `
1-
#1760000
0-
#1770000
b1010 `
1-
#1780000
0-
#1790000
b1011 `
1-
#1800000
0-
b10 _
b11 ~
1}
0|
#1810000
b111111 ,
b111111 D
b111111 k
b111111 +
b111111 C
b111111 l
b111111 *
b111111 B
b111111 m
b0 ?
b0 \
b0 a
1-
#1820000
0-
#1830000
1-
#1840000
0-
#1850000
1-
#1860000
0-
#1870000
1-
#1880000
0-
#1890000
1-
#1900000
0-
b10 _
#1910000
1-
#1920000
0-
#1930000
1-
#1940000
0-
#1950000
1-
#1960000
0-
#1970000
1-
#1980000
0-
#1990000
1-
#2000000
16
0K
0-
0>
b101 .
b101 2
b10100101 /
b10100101 4
b10100101 O
b10100101 ""
